spyder_terminal/__init__.py
spyder_terminal/terminalplugin.py
spyder_terminal/server/__init__.py
spyder_terminal/server/main.py
spyder_terminal/server/routes.py
spyder_terminal/server/logic/__init__.py
spyder_terminal/server/logic/term_manager.py
spyder_terminal/server/rest/__init__.py
spyder_terminal/server/rest/term_rest.py
spyder_terminal/server/static/index.html
spyder_terminal/server/static/components/fetch/.bower.json
spyder_terminal/server/static/components/fetch/bower.json
spyder_terminal/server/static/components/fetch/fetch.js
spyder_terminal/server/static/components/jquery/.bower.json
spyder_terminal/server/static/components/jquery/bower.json
spyder_terminal/server/static/components/jquery/dist/core.js
spyder_terminal/server/static/components/jquery/dist/jquery.js
spyder_terminal/server/static/components/jquery/dist/jquery.min.js
spyder_terminal/server/static/components/jquery/dist/jquery.slim.js
spyder_terminal/server/static/components/jquery/dist/jquery.slim.min.js
spyder_terminal/server/static/components/jquery/external/sizzle/dist/sizzle.js
spyder_terminal/server/static/components/jquery/external/sizzle/dist/sizzle.min.js
spyder_terminal/server/static/components/jquery/src/.eslintrc.json
spyder_terminal/server/static/components/jquery/src/ajax.js
spyder_terminal/server/static/components/jquery/src/attributes.js
spyder_terminal/server/static/components/jquery/src/callbacks.js
spyder_terminal/server/static/components/jquery/src/core.js
spyder_terminal/server/static/components/jquery/src/css.js
spyder_terminal/server/static/components/jquery/src/data.js
spyder_terminal/server/static/components/jquery/src/deferred.js
spyder_terminal/server/static/components/jquery/src/deprecated.js
spyder_terminal/server/static/components/jquery/src/dimensions.js
spyder_terminal/server/static/components/jquery/src/effects.js
spyder_terminal/server/static/components/jquery/src/event.js
spyder_terminal-0.2.4.dist-info/DESCRIPTION.rst
spyder_terminal-0.2.4.dist-info/METADATA
spyder_terminal-0.2.4.dist-info/RECORD
spyder_terminal-0.2.4.dist-info/WHEEL
spyder_terminal-0.2.4.dist-info/metadata.json
spyder_terminal-0.2.4.dist-info/top_level.txt
