Metadata-Version: 2.0
Name: spyder-terminal
Version: 0.2.4
Summary: Spyder Plugin for displaying a virtual terminal (OS independent) inside the main Spyder window
Home-page: https://github.com/spyder-ide/spyder-terminal
Author: Spyder Project Contributors
Author-email: admin@spyder-ide.org
License: MIT
Keywords: Spyder,Plugin
Platform: UNKNOWN
Classifier: Development Status :: 4 - Beta
Classifier: Intended Audience :: Developers
Classifier: Intended Audience :: Science/Research
Classifier: License :: OSI Approved :: MIT License
Classifier: Operating System :: MacOS
Classifier: Operating System :: Microsoft :: Windows
Classifier: Operating System :: POSIX :: Linux
Classifier: Programming Language :: Python :: 2.7
Classifier: Programming Language :: Python :: 3.5
Classifier: Programming Language :: Python :: 3.6
Requires-Dist: coloredlogs
Requires-Dist: pexpect
Requires-Dist: requests
Requires-Dist: spyder (>=3.2.0)
Requires-Dist: tornado
